{
  "users": [
    {
      "id": "admin",
      "password": "admin1234",
      "access": "admin"
    },
    {
      "id": "default_user",
      "password": "default_password",
      "access": "user"
    },
    {
      "id": "user",
      "password": "1234",
      "access": "user"
    }
  ],
  "cars": [
    {
      "id": "ford-focus2013",
      "image": "./image/ford-focus2013.png",
      "color": "red",
      "gearbox": "Автоматична",
      "fuel_type": "Бензин",
      "color": "червоний",
      "gearbox": "автоматична",
      "fuel-type": "бензин",
      "brand": "Ford",
      "model": "Focus",
      "year": "2013",
      "class price": "econom",
      "price": 30,
      "category": "category1",
      "wheeldrive": "Передній привід",
      "enginesize": "1.6",
      "gasoline": "7.8 л/100 км"
    },
    {
      "id": "toyota-corolla2019",
      "image": "./image/toyota-corolla2019.png",
      "color": "white",
      "gearbox": "Полуавтоматчна",
      "fuel_type": "Дизель",
      "color": "білий",
      "gearbox": "механічна",
      "fuel-type": "дизельне паливо",
      "brand": "Toyota",
      "model": "Corolla",
      "year": "2019",
      "class price": "medium",
      "price": 40,
      "category": "category1",
      "wheeldrive": "Передній привід",
      "enginesize": "1.8",
      "gasoline": "6.7 л/100 км"
    },
    {
      "id": "ford-fusion2019",
      "image": "./image/ford-fusion2019.png",
      "color": "white",
      "gearbox": "Автоматична",
      "fuel_type": "Бензин",
      "color": "білий",
      "gearbox": "автоматична",
      "fuel-type": "бензин",
      "brand": "Ford",
      "model": "Fusion",
      "year": "2019",
      "class price": "business",
      "price": 50,
      "category": "category1",
      "wheeldrive": "Повний привід",
      "enginesize": "2.5",
      "gasoline": "8.5 л/100 км"
    },
    {
      "id": "chevrolet-impala2020",
      "image": "./image/chevrolet-impala2020.png",
      "color": "red",
      "gearbox": "Автоматична",
      "fuel_type": "Бензин",
      "color": "червоний",
      "gearbox": "автоматична",
      "fuel-type": "бензин",
      "brand": "Chevrolet",
      "model": "Impala",
      "year": "2020",
      "class price": "premium",
      "price": 60,
      "category": "category1",
      "wheeldrive": "Передній привід",
      "enginesize": "3.6",
      "gasoline": "9.8 л/100 км"
    },
    {
      "id": "honda-accord2015",
      "image": "./image/honda-accord2015.png",
      "color": "blue",
      "gearbox": "Автоматична",
      "fuel_type": "Бензин",
      "color": "синій",
      "gearbox": "автоматична",
      "fuel-type": "бензин",
      "brand": "Honda",
      "model": "Accord",
      "year": "2015",
      "class price": "medium",
      "price": 40,
      "category": "category1",
      "wheeldrive": "Повний привід",
      "enginesize": "2.4",
      "gasoline": " 7.6 л/100 км"
    },
    {
      "id": "toyota-corolla2014",
      "image": "./image/toyota-corolla2014.png",
      "color": "dark",
      "gearbox": "Механічна",
      "fuel_type": "Бензин",
      "color": "чорний",
      "gearbox": "механічна",
      "fuel-type": "бензин",
      "brand": "Toyota",
      "model": "Corolla",
      "year": "2014",
      "class price": "econom",
      "price": 30,
      "category": "category2",
      "wheeldrive": "Передній привід",
      "enginesize": "1.8",
      "gasoline": "6.5 л/100 км"
    },
    {
      "id": "nissan-sentra2017",
      "image": "./image/nissan-sentra2017.png",
      "color": "light black",
      "gearbox": "Автоматична",
      "fuel_type": "Бензин",
      "color": "сріблястий",
      "gearbox": "автоматична",
      "fuel-type": "бензин",
      "brand": "Nissan",
      "model": "Sentra",
      "year": "2017",
      "class price": "econom",
      "price": 30,
      "category": "category1",
      "wheeldrive": "Передній привід",
      "enginesize": "1.8",
      "gasoline": "7.2 л/100 км"
    },
    {
      "id": "hyundai-sonata2016",
      "image": "./image/hyundai-sonata2016.png",
      "color": "black",
      "gearbox": "Автоматична",
      "fuel_type": "Бензин",
      "color": "чорний",
      "gearbox": "автоматична",
      "fuel-type": "бензин",
      "brand": "Hyundai",
      "model": "Sonata",
      "year": "2016",
      "class price": "medium",
      "price": 40,
      "category": "category1",
      "wheeldrive": "Передній привід",
      "enginesize": "2.4",
      "gasoline": "8.1 л/100 км"
    },
    {
      "id": "kia-soul2018",
      "image": "./image/kia-soul2018.png",
      "color": "white",
      "gearbox": "Автоматична",
      "fuel_type": "Бензин",
      "color": "білий",
      "gearbox": "автоматична",
      "fuel-type": "бензин",
      "brand": "Kia",
      "model": "Soul",
      "year": "2018",
      "class price": "medium",
      "price": 40,
      "category": "category3",
      "wheeldrive": "Повний привід",
      "enginesize": "2.0",
      "gasoline": "7.8 л/100 км"
    },
    {
      "id": "ford-escape2019",
      "image": "./image/ford-escape2019.png",
      "color": "blue",
      "gearbox": "Автоматична",
      "fuel_type": "Бензин",
      "color": "синій",
      "gearbox": "автоматична",
      "fuel-type": "бензин",
      "brand": "Ford",
      "model": "Escape",
      "year": "2019",
      "class price": "business",
      "price": 50,
      "category": "category4",
      "wheeldrive": "Повний привід",
      "enginesize": "1.5",
      "gasoline": "8.0 л/100 км"
    },
    {
      "id": "chevrolet-equinox2020",
      "image": "./image/chevrolet-equinox2020.png",
      "color": "red",
      "gearbox": "Автоматична",
      "fuel_type": "Бензин",
      "color": "червоний",
      "gearbox": "автоматична",
      "fuel-type": "бензин",
      "brand": "Chevrolet",
      "model": "Equinox",
      "year": "2020",
      "class price": "business",
      "price": 50,
      "category": "category4",
      "wheeldrive": "Повний привід",
      "enginesize": "1.5",
      "gasoline": "8.3 л/100 км"
    },
    {
      "id": "honda-cr-v2016",
      "image": "./image/honda-cr-v2016.png",
      "color": "red",
      "gearbox": "Автоматична",
      "fuel_type": "Бензин",
      "color": "червоний",
      "gearbox": "автоматична",
      "fuel-type": "бензин",
      "brand": "Honda",
      "model": "CR-V",
      "year": "2016",
      "class price": "business",
      "price": 50,
      "category": "category4",
      "wheeldrive": "Повний привід",
      "enginesize": "2.4",
      "gasoline": "7.8 л/100 км"
    },
    {
      "id": "toyota-rav42017",
      "image": "./image/toyota-rav42017.png",
      "color": "black",
      "gearbox": "Автоматична",
      "fuel_type": "Бензин",
      "color": "чорний",
      "gearbox": "автоматична",
      "fuel-type": "бензин",
      "brand": "Toyota",
      "model": "RAV4",
      "year": "2017",
      "class price": "business",
      "price": 50,
      "category": "category2",
      "wheeldrive": "Повний привід",
      "enginesize": "2.5",
      "gasoline": "8.0 л/100 км"
    },
    {
      "id": "nissan-rogue2018",
      "image": "./image/nissan-rogue2018.png",
      "color": "blue",
      "gearbox": "Автоматична",
      "fuel_type": "Бензин",
      "color": "синій",
      "gearbox": "автоматична",
      "fuel-type": "бензин",
      "brand": "Nissan",
      "model": "Rogue",
      "year": "2018",
      "class price": "premium",
      "price": 60,
      "category": "category2",
      "wheeldrive": "Передній привід",
      "enginesize": "2.5",
      "gasoline": "7.6   л/100 км"
    },
    {
      "id": "hyundai-tucson2019",
      "image": "./image/hyundai-tucson2019.png",
      "color": "gray",
      "gearbox": "Автоматична",
      "fuel_type": "Бензин",
      "color": "сріблястий",
      "gearbox": "автоматична",
      "fuel-type": "бензин",
      "brand": "Hyundai",
      "model": "Tucson",
      "year": "2019",
      "class price": "business",
      "price": 50,
      "category": "category3",
      "wheeldrive": "Передній привід",
      "enginesize": "2.0",
      "gasoline": "8.4 л/100 км"
    },
    {
      "id": "kia-sportage2020",
      "image": "./image/kia-sportage2020.png",
      "color": "red",
      "gearbox": "Автоматична",
      "fuel_type": "Бензин",
      "color": "червоний",
      "gearbox": "автоматична",
      "fuel-type": "бензин",
      "brand": "Kia",
      "model": "Sportage",
      "year": "2020",
      "class price": "premium",
      "price": 60,
      "category": "category4",
      "wheeldrive": "Повний привід",
      "enginesize": "2.4",
      "gasoline": "8.1 л/100 км"
    },
    {
      "id": "ford-edge2017",
      "image": "./image/ford-edge2017.png",
      "color": "black",
      "gearbox": "Автоматична",
      "fuel_type": "Бензин",
      "color": "чорний",
      "gearbox": "автоматична",
      "fuel-type": "бензин",
      "brand": "Ford",
      "model": "Edge",
      "year": "2017",
      "class price": "premium",
      "price": 60,
      "category": "category3",
      "wheeldrive": "Передній привід",
      "enginesize": "2.0",
      "gasoline": "9.8 л/100 км"
    },
    {
      "id": "chevrolet-traverse2018",
      "image": "./image/chevrolet-traverse2018.png",
      "color": "white",
      "gearbox": "Автоматична",
      "fuel_type": "Бензин",
      "color": "темно-червоний",
      "gearbox": "автоматична",
      "fuel-type": "бензин",
      "brand": "Chevrolet",
      "model": "Traverse",
      "year": "2018",
      "class price": "luxury",
      "price": 70,
      "category": "category3",
      "wheeldrive": "Передній привід",
      "enginesize": "3.6",
      "gasoline": "10.8 л/100 км"
    },
    {
      "id": "toyota-camry2015",
      "image": "./image/toyota-camry2015.png",
      "color": "білий",
      "gearbox": "автоматична",
      "fuel-type": "дизельне паливо",
      "brand": "Toyota",
      "model": "Camry",
      "year": "2015",
      "class price": "medium",
      "price": 40,
      "category": "category3",
      "wheeldrive": "Передній привід",
      "enginesize": "2.5",
      "gasoline": "8.2 л/100 км"
    },
    {
      "id": "honda-civic2014",
      "image": "./image/honda-civic2014.png",
      "color": "blue",
      "gearbox": "Механічна",
      "fuel_type": "Дизель",
      "color": "синій",
      "gearbox": "механічна",
      "fuel-type": "дизельне паливо",
      "brand": "Honda",
      "model": "Civic",
      "year": "2014",
      "class price": "econom",
      "price": 30,
      "category": "category3",
      "wheeldrive": "Передній привід",
      "enginesize": "1.8",
      "gasoline": "6.8 л/100 км"
    },
    {
      "id": "chevrolet-malibu2016",
      "image": "./image/chevrolet-malibu2016.png",
      "color": "black",
      "gearbox": "Автоматична",
      "fuel_type": "Дизель",
      "color": "чорний",
      "gearbox": "автоматична",
      "fuel-type": "дизельне паливо",
      "brand": "Chevrolet",
      "model": "Malibu",
      "year": "2016",
      "class price": "medium",
      "price": 40,
      "category": "category3",
      "wheeldrive": "Передній привід",
      "enginesize": "2.5",
      "gasoline": "8.4 л/100 км"
    },
    {
      "id": "nissan-altima2017",
      "image": "./image/nissan-altima2017.png",
      "color": "сріблястий",
      "gearbox": "автоматична",
      "fuel-type": "дизельне паливо",
      "brand": "Nissan",
      "model": "Altima",
      "year": "2017",
      "class price": "medium",
      "price": 40,
      "category": "category3",
      "wheeldrive": "Повний привід",
      "enginesize": "2.5",
      "gasoline": "7.5 л/100 км"
    },
    {
      "id": "hyundai-elantra2015",
      "image": "./image/hyundai-elantra2015.png",
      "color": "сріблястий",
      "gearbox": "автоматична",
      "fuel-type": "дизельне паливо",
      "brand": "Hyundai",
      "model": "Elantra",
      "year": "2015",
      "class price": "econom",
      "price": 30,
      "category": "category3",
      "wheeldrive": "Передній привід",
      "enginesize": "1.8",
      "gasoline": "7.1 л/100 км"
    },
    {
      "id": "kia-optima2018",
      "image": "./image/kia-optima2018.png",
      "color": "білий",
      "gearbox": "автоматична",
      "fuel-type": "дизельне паливо",
      "brand": "Kia",
      "model": "Optima",
      "year": "2018",
      "class price": "business",
      "price": 50,
      "category": "category1",
      "wheeldrive": "Повний привід",
      "enginesize": "2.4",
      "gasoline": "8.1 л/100 км"
    },
    {
      "id": "volkswagen-jetta2019",
      "image": "./image/volkswagen-jetta2019.png",
      "color": "білий",
      "gearbox": "автоматична",
      "fuel-type": "дизельне паливо",
      "brand": "Volkswagen",
      "model": "Jetta",
      "year": "2019",
      "class price": "medium",
      "price": 40,
      "category": "category1",
      "wheeldrive": "Передній привід",
      "enginesize": "1.4",
      "gasoline": "6.8 л/100 км"
    },
    {
      "id": "bmw-320d2020",
      "image": "./image/bmw-320d2020.png",
      "color": "чорний",
      "gearbox": "автоматична",
      "fuel-type": "дизельне паливо",
      "brand": "BMW",
      "model": "320d",
      "year": "2020",
      "class price": "luxury",
      "price": 70,
      "category": "category5",
      "wheeldrive": "Повний привід",
      "enginesize": "2.0",
      "gasoline": "4.3 л/100 км"
    },
    {
      "id": "audi-a32019",
      "image": "./image/audi-a32019.png",
      "color": "білий",
      "gearbox": "автоматична",
      "fuel-type": "дизельне паливо",
      "brand": "Audi",
      "model": "A3",
      "year": "2019",
      "class price": "luxury",
      "price": 70,
      "category": "category5",
      "wheeldrive": "Повний привід",
      "enginesize": "2.0",
      "gasoline": "6.2 л/100 км"
    },
    {
      "id": "mercedes-c2202018",
      "image": "./image/mercedes-c2202018.png",
      "color": "сріблястий",
      "gearbox": "автоматична",
      "fuel-type": "дизельне паливо",
      "brand": "Mercedes",
      "model": "C220",
      "year": "2018",
      "class price": "luxury",
      "price": 70,
      "category": "category5",
      "wheeldrive": "Повний привід",
      "enginesize": "2.1",
      "gasoline": "5.1 л/100 км"
    },
    {
      "id": "renault-megane2019",
      "image": "./image/renault-megane2019.png",
      "color": "білий",
      "gearbox": "автоматична",
      "fuel-type": "дизельне паливо",
      "brand": "Renault",
      "model": "Megane",
      "year": "2019",
      "class price": "medium",
      "price": 40,
      "category": "category5",
      "wheeldrive": "Повний привід",
      "enginesize": "1.3",
      "gasoline": "6.2 л/100 км"
    },
    {
      "id": "volvo-s602018",
      "image": "./image/volvo-s602018.png",
      "color": "red",
      "gearbox": "Автоматична",
      "fuel_type": "Дизель",
      "color": "червоний",
      "gearbox": "автоматична",
      "fuel-type": "дизельне паливо",
      "brand": "Volvo",
      "model": "S60",
      "year": "2018",
      "class price": "premium",
      "price": 60,
      "category": "category5",
      "wheeldrive": "Повний привід",
      "enginesize": "2.0",
      "gasoline": "7.0 л/100 км"
    }
  ],
  "access_rights": [
    {
      "access": "admin",
      "data": "cars",
      "can_see": true,
      "can_edit": true,
      "can_add": true,
      "can_delete": true
    },
    {
      "access": "admin",
      "data": "cars_confidential",
      "can_see": true,
      "can_edit": true,
      "can_add": true,
      "can_delete": true
    },
    {
      "access": "admin",
      "data": "users",
      "can_see": true,
      "can_edit": true,
      "can_add": true,
      "can_delete": true
    },
    {
      "access": "user",
      "data": "cars",
      "can_see": true,
      "can_edit": false,
      "can_add": false,
      "can_delete": false
    },
    {
      "access": "user",
      "data": "cars_confidential",
      "can_see": false,
      "can_edit": false,
      "can_add": false,
      "can_delete": false
    },
    {
      "access": "user",
      "data": "users",
      "can_see": true,
      "can_edit": true,
      "can_add": true,
      "can_delete": false
    }
  ]
}